dltype/__init__.py
dltype/_lib/__init__.py
dltype/_lib/_constants.py
dltype/_lib/_core.py
dltype/_lib/_dependency_utilities.py
dltype/_lib/_dltype_context.py
dltype/_lib/_dtypes.py
dltype/_lib/_errors.py
dltype/_lib/_numpy_tensors.py
dltype/_lib/_parser.py
dltype/_lib/_symbolic_expressions.py
dltype/_lib/_tensor_type_base.py
dltype/_lib/_torch_tensors.py
dltype/_lib/_universal_tensors.py
dltype/tests/__init__.py
dltype/tests/dltype_test.py
dltype/tests/interop_test.py
dltype/tests/parser_test.py
dltype-0.10.0.dist-info/licenses/LICENSE
dltype-0.10.0.dist-info/METADATA
dltype-0.10.0.dist-info/WHEEL
dltype-0.10.0.dist-info/top_level.txt
dltype-0.10.0.dist-info/RECORD
