Metadata-Version: 2.4
Name: dltype
Version: 0.10.0
Summary: An extremely lightweight typing library for torch tensors or numpy arrays. Supports runtime shape checking and data type validation.
License-Expression: Apache-2.0
Project-URL: homepage, https://github.com/stackav-oss/dltype
Project-URL: repository, https://github.com/stackav-oss/dltype.git
Keywords: pytorch,numpy,shape check,type check
Requires-Python: >=3.10
License-File: LICENSE
Requires-Dist: pydantic>=2.0; python_version < "3.14"
Requires-Dist: pydantic>=2.12; python_version >= "3.14"
Requires-Dist: pydantic-settings>=2.12.0
Provides-Extra: jax
Requires-Dist: jax>=0.6.2; extra == "jax"
Provides-Extra: numpy
Requires-Dist: numpy; extra == "numpy"
Provides-Extra: torch
Requires-Dist: torch>=1.11.0; extra == "torch"
Dynamic: license-file
